L3/simple.vhd
----------------------------------------------------------------------------------
-- Design Name: 
-- Module Name:    simple - simple_counter_arch 
-- Target Devices: 
-- Tool versions: 
-- Description: 
--
-- Additional Comments: kod na podstawie
--		Majewski, Zbysinski "Uklady FPGA w przykladach"
--
----------------------------------------------------------------------------------
library IEEE;
use IEEE.STD_LOGIC_1164.ALL;
use IEEE.numeric_std.ALL;


entity simple is
	generic ( NBit : natural := 8 );
   port  ( clk : in  STD_LOGIC;
           rst : in  STD_LOGIC;
-- INOUT -- signal 'q' is set from 'inside' the entity, but also read outside as its output
             q : inout  unsigned( NBit-1 downto 0)
				 );
end simple;

architecture simple_counter_arch of simple is

BEGIN
  PROCESS(clk, rst)
  BEGIN
	IF rst = '0' THEN 
		q <= ('1','0','1','0', OTHERS => '0');
	ELSIF (clk'event and clk='1') THEN
    -- you can add like this:
    	   q <= q + 1;
    -- or like this
	--   q <= q + "00000001";
    -- but can't do it this way (why?)
	 --  q <= q + '1';
		END IF;
  END PROCESS;
END simple_counter_arch;

L3/simple_tb.vhd
LIBRARY ieee;
library std;
USE ieee.std_logic_1164.ALL;
USE ieee.numeric_std.ALL;
use std.textio.all;

 
ENTITY simple_tb IS
END simple_tb;
 
ARCHITECTURE behavior OF simple_tb IS 
 
    -- UUT (Unit Under Test)
    COMPONENT simple
    PORT(
         clk : IN  std_logic;
         rst : IN  std_logic;
         q : INOUT  unsigned(7 downto 0)
        );
    END COMPONENT;
    
   -- input signals
   signal clk : std_logic := '0';
   signal rst : std_logic := '0';

   -- input/output signal
   signal qq : unsigned(7 downto 0);

   -- set clock period 
   constant clk_period : time := 20 ns;
 
BEGIN
	-- instantiate UUT
   uut: simple PORT MAP (
          clk => clk,
          rst => rst,
          q   => qq
        );
   
   -- clock management process
   -- no sensitivity list, but uses 'wait'
   clk_process :PROCESS
   BEGIN
		clk <= '0';
		WAIT FOR clk_period/2;
		clk <= '1';
		WAIT FOR clk_period/2;
   END PROCESS;
 

   -- stimulating process
   stim_proc: PROCESS
     variable my_line : line;
   BEGIN		
      -- let it run 
      wait for 100 ns;
      -- apply reset
      rst <= '1';
      -- czekam 700 ns, bo musi dodac 35 razy jedynke do licznika (t = 35*clk_period)
      wait for 700 ns;
      -- and let it go
      -- wypisuje wartosc licznika na wyjscie
      write(my_line, to_integer(qq));
      writeline(output, my_line);
      -- licznik znowu bedzie miec wartosc 160
      rst <= '0';
      -- czekam
      wait for 50 ns;
      --
      ---- rozpoczynam odliczanie
      rst <= '1';
      -- czekam 440 ns, bo musi teraz sie zmienic 22 razy (t = 22*clk_period)
      wait for 440 ns;
      -- wypisuje wartosc licznika
      write(my_line, to_integer(qq));
      writeline(output, my_line);
      wait;
   END PROCESS;	
END;

L3/simple.vcd
$date
  Tue Apr 20 20:44:24 2021
$end
$version
  GHDL v0
$end
$timescale
  1 fs
$end
$scope module standard $end
$upscope $end
$scope module std_logic_1164 $end
$upscope $end
$scope module numeric_std $end
$upscope $end
$scope module textio $end
$upscope $end
$scope module simple_tb $end
$var reg 1 ! clk $end
$var reg 1 " rst $end
$var reg 8 # qq[7:0] $end
$scope module uut $end
$var reg 1 $ clk $end
$var reg 1 % rst $end
$var reg 8 & q[7:0] $end
$upscope $end
$upscope $end
$enddefinitions $end
#0
0!
0"
b10100000 #
0$
0%
b10100000 &
#10000000
1!
1$
#20000000
0!
0$
#30000000
1!
1$
#40000000
0!
0$
#50000000
1!
1$
#60000000
0!
0$
#70000000
1!
1$
#80000000
0!
0$
#90000000
1!
1$
#100000000
0!
1"
0$
1%
#110000000
1!
b10100001 #
1$
b10100001 &
#120000000
0!
0$
#130000000
1!
b10100010 #
1$
b10100010 &
#140000000
0!
0$
#150000000
1!
b10100011 #
1$
b10100011 &
#160000000
0!
0$
#170000000
1!
b10100100 #
1$
b10100100 &
#180000000
0!
0$
#190000000
1!
b10100101 #
1$
b10100101 &
#200000000
0!
0$
#210000000
1!
b10100110 #
1$
b10100110 &
#220000000
0!
0$
#230000000
1!
b10100111 #
1$
b10100111 &
#240000000
0!
0$
#250000000
1!
b10101000 #
1$
b10101000 &
#260000000
0!
0$
#270000000
1!
b10101001 #
1$
b10101001 &
#280000000
0!
0$
#290000000
1!
b10101010 #
1$
b10101010 &
#300000000
0!
0$
#310000000
1!
b10101011 #
1$
b10101011 &
#320000000
0!
0$
#330000000
1!
b10101100 #
1$
b10101100 &
#340000000
0!
0$
#350000000
1!
b10101101 #
1$
b10101101 &
#360000000
0!
0$
#370000000
1!
b10101110 #
1$
b10101110 &
#380000000
0!
0$
#390000000
1!
b10101111 #
1$
b10101111 &
#400000000
0!
0$
#410000000
1!
b10110000 #
1$
b10110000 &
#420000000
0!
0$
#430000000
1!
b10110001 #
1$
b10110001 &
#440000000
0!
0$
#450000000
1!
b10110010 #
1$
b10110010 &
#460000000
0!
0$
#470000000
1!
b10110011 #
1$
b10110011 &
#480000000
0!
0$
#490000000
1!
b10110100 #
1$
b10110100 &
#500000000
0!
0$
#510000000
1!
b10110101 #
1$
b10110101 &
#520000000
0!
0$
#530000000
1!
b10110110 #
1$
b10110110 &
#540000000
0!
0$
#550000000
1!
b10110111 #
1$
b10110111 &
#560000000
0!
0$
#570000000
1!
b10111000 #
1$
b10111000 &
#580000000
0!
0$
#590000000
1!
b10111001 #
1$
b10111001 &
#600000000
0!
0$
#610000000
1!
b10111010 #
1$
b10111010 &
#620000000
0!
0$
#630000000
1!
b10111011 #
1$
b10111011 &
#640000000
0!
0$
#650000000
1!
b10111100 #
1$
b10111100 &
#660000000
0!
0$
#670000000
1!
b10111101 #
1$
b10111101 &
#680000000
0!
0$
#690000000
1!
b10111110 #
1$
b10111110 &
#700000000
0!
0$
#710000000
1!
b10111111 #
1$
b10111111 &
#720000000
0!
0$
#730000000
1!
b11000000 #
1$
b11000000 &
#740000000
0!
0$
#750000000
1!
b11000001 #
1$
b11000001 &
#760000000
0!
0$
#770000000
1!
b11000010 #
1$
b11000010 &
#780000000
0!
0$
#790000000
1!
b11000011 #
1$
b11000011 &
#800000000
0!
0"
b10100000 #
0$
0%
b10100000 &
#810000000
1!
1$
#820000000
0!
0$
#830000000
1!
1$
#840000000
0!
0$
#850000000
1!
1"
b10100001 #
1$
1%
b10100001 &
#860000000
0!
0$
#870000000
1!
b10100010 #
1$
b10100010 &
#880000000
0!
0$
#890000000
1!
b10100011 #
1$
b10100011 &
#900000000
0!
0$
#910000000
1!
b10100100 #
1$
b10100100 &
#920000000
0!
0$
#930000000
1!
b10100101 #
1$
b10100101 &
#940000000
0!
0$
#950000000
1!
b10100110 #
1$
b10100110 &
#960000000
0!
0$
#970000000
1!
b10100111 #
1$
b10100111 &
#980000000
0!
0$
#990000000
1!
b10101000 #
1$
b10101000 &
#1000000000
0!
0$
#1010000000
1!
b10101001 #
1$
b10101001 &
#1020000000
0!
0$
#1030000000
1!
b10101010 #
1$
b10101010 &
#1040000000
0!
0$
#1050000000
1!
b10101011 #
1$
b10101011 &
#1060000000
0!
0$
#1070000000
1!
b10101100 #
1$
b10101100 &
#1080000000
0!
0$
#1090000000
1!
b10101101 #
1$
b10101101 &
#1100000000
0!
0$
#1110000000
1!
b10101110 #
1$
b10101110 &
#1120000000
0!
0$
#1130000000
1!
b10101111 #
1$
b10101111 &
#1140000000
0!
0$
#1150000000
1!
b10110000 #
1$
b10110000 &
#1160000000
0!
0$
#1170000000
1!
b10110001 #
1$
b10110001 &
#1180000000
0!
0$
#1190000000
1!
b10110010 #
1$
b10110010 &
#1200000000
0!
0$
#1210000000
1!
b10110011 #
1$
b10110011 &
#1220000000
0!
0$
#1230000000
1!
b10110100 #
1$
b10110100 &
#1240000000
0!
0$
#1250000000
1!
b10110101 #
1$
b10110101 &
#1260000000
0!
0$
#1270000000
1!
b10110110 #
1$
b10110110 &
#1280000000
0!
0$
#1290000000
1!
b10110111 #
1$
b10110111 &
#1300000000
0!
0$
#1310000000
1!
b10111000 #
1$
b10111000 &
#1320000000
0!
0$
#1330000000
1!
b10111001 #
1$
b10111001 &
#1340000000
0!
0$
#1350000000
1!
b10111010 #
1$
b10111010 &
#1360000000
0!
0$
#1370000000
1!
b10111011 #
1$
b10111011 &
#1380000000
0!
0$
#1390000000
1!
b10111100 #
1$
b10111100 &
#1400000000
0!
0$
#1410000000
1!
b10111101 #
1$
b10111101 &
#1420000000
0!
0$
#1430000000
1!
b10111110 #
1$
b10111110 &
#1440000000
0!
0$
#1450000000
1!
b10111111 #
1$
b10111111 &
#1460000000
0!
0$
#1470000000
1!
b11000000 #
1$
b11000000 &
#1480000000
0!
0$
#1490000000
1!
b11000001 #
1$
b11000001 &
#1500000000
0!
0$
#1510000000
1!
b11000010 #
1$
b11000010 &
#1520000000
0!
0$
#1530000000
1!
b11000011 #
1$
b11000011 &
#1540000000
0!
0$
#1550000000
1!
b11000100 #
1$
b11000100 &
#1560000000
0!
0$
#1570000000
1!
b11000101 #
1$
b11000101 &
#1580000000
0!
0$
#1590000000
1!
b11000110 #
1$
b11000110 &
#1600000000
0!
0$
#1610000000
1!
b11000111 #
1$
b11000111 &
#1620000000
0!
0$
#1630000000
1!
b11001000 #
1$
b11001000 &
#1640000000
0!
0$
#1650000000
1!
b11001001 #
1$
b11001001 &
#1660000000
0!
0$
#1670000000
1!
b11001010 #
1$
b11001010 &
#1680000000
0!
0$
#1690000000
1!
b11001011 #
1$
b11001011 &
#1700000000
0!
0$
#1710000000
1!
b11001100 #
1$
b11001100 &
#1720000000
0!
0$
#1730000000
1!
b11001101 #
1$
b11001101 &
#1740000000
0!
0$
#1750000000
1!
b11001110 #
1$
b11001110 &
#1760000000
0!
0$
#1770000000
1!
b11001111 #
1$
b11001111 &
#1780000000
0!
0$
#1790000000
1!
b11010000 #
1$
b11010000 &
#1800000000
0!
0$
#1810000000
1!
b11010001 #
1$
b11010001 &
#1820000000
0!
0$
#1830000000
1!
b11010010 #
1$
b11010010 &
#1840000000
0!
0$
#1850000000
1!
b11010011 #
1$
b11010011 &
#1860000000
0!
0$
#1870000000
1!
b11010100 #
1$
b11010100 &
#1880000000
0!
0$
#1890000000
1!
b11010101 #
1$
b11010101 &
#1900000000
0!
0$
#1910000000
1!
b11010110 #
1$
b11010110 &
#1920000000
0!
0$
#1930000000
1!
b11010111 #
1$
b11010111 &
#1940000000
0!
0$
#1950000000
1!
b11011000 #
1$
b11011000 &
#1960000000
0!
0$
#1970000000
1!
b11011001 #
1$
b11011001 &
#1980000000
0!
0$
#1990000000
1!
b11011010 #
1$
b11011010 &
#2000000000
0!
0$
#2010000000
1!
b11011011 #
1$
b11011011 &
#2020000000
0!
0$
#2030000000
1!
b11011100 #
1$
b11011100 &
#2040000000
0!
0$
#2050000000
1!
b11011101 #
1$
b11011101 &
#2060000000
0!
0$
#2070000000
1!
b11011110 #
1$
b11011110 &
#2080000000
0!
0$
#2090000000
1!
b11011111 #
1$
b11011111 &
#2100000000
0!
0$
#2110000000
1!
b11100000 #
1$
b11100000 &
#2120000000
0!
0$
#2130000000
1!
b11100001 #
1$
b11100001 &
#2140000000
0!
0$
#2150000000
1!
b11100010 #
1$
b11100010 &
#2160000000
0!
0$
#2170000000
1!
b11100011 #
1$
b11100011 &
#2180000000
0!
0$
#2190000000
1!
b11100100 #
1$
b11100100 &
#2200000000
0!
0$
#2210000000
1!
b11100101 #
1$
b11100101 &
#2220000000
0!
0$
#2230000000
1!
b11100110 #
1$
b11100110 &
#2240000000
0!
0$
#2250000000
1!
b11100111 #
1$
b11100111 &
#2260000000
0!
0$
#2270000000
1!
b11101000 #
1$
b11101000 &
#2280000000
0!
0$
#2290000000
1!
b11101001 #
1$
b11101001 &
#2300000000
0!
0$
#2310000000
1!
b11101010 #
1$
b11101010 &
#2320000000
0!
0$
#2330000000
1!
b11101011 #
1$
b11101011 &
#2340000000
0!
0$
#2350000000
1!
b11101100 #
1$
b11101100 &
#2360000000
0!
0$
#2370000000
1!
b11101101 #
1$
b11101101 &
#2380000000
0!
0$
#2390000000
1!
b11101110 #
1$
b11101110 &
#2400000000
0!
0$
#2410000000
1!
b11101111 #
1$
b11101111 &
#2420000000
0!
0$
#2430000000
1!
b11110000 #
1$
b11110000 &
#2440000000
0!
0$
#2450000000
1!
b11110001 #
1$
b11110001 &
#2460000000
0!
0$
#2470000000
1!
b11110010 #
1$
b11110010 &
#2480000000
0!
0$
#2490000000
1!
b11110011 #
1$
b11110011 &
#2500000000
0!
0$
#2510000000
1!
b11110100 #
1$
b11110100 &
#2520000000
0!
0$
#2530000000
1!
b11110101 #
1$
b11110101 &
#2540000000
0!
0$
#2550000000
1!
b11110110 #
1$
b11110110 &
#2560000000
0!
0$
#2570000000
1!
b11110111 #
1$
b11110111 &
#2580000000
0!
0$
#2590000000
1!
b11111000 #
1$
b11111000 &
#2600000000
0!
0$
#2610000000
1!
b11111001 #
1$
b11111001 &
#2620000000
0!
0$
#2630000000
1!
b11111010 #
1$
b11111010 &
#2640000000
0!
0$
#2650000000
1!
b11111011 #
1$
b11111011 &
#2660000000
0!
0$
#2670000000
1!
b11111100 #
1$
b11111100 &
#2680000000
0!
0$
#2690000000
1!
b11111101 #
1$
b11111101 &
#2700000000
0!
0$
#2710000000
1!
b11111110 #
1$
b11111110 &
#2720000000
0!
0$
#2730000000
1!
b11111111 #
1$
b11111111 &
#2740000000
0!
0$
#2750000000
1!
b00000000 #
1$
b00000000 &
#2760000000
0!
0$
#2770000000
1!
b00000001 #
1$
b00000001 &
#2780000000
0!
0$
#2790000000
1!
b00000010 #
1$
b00000010 &
#2800000000
0!
0$
#2810000000
1!
b00000011 #
1$
b00000011 &
#2820000000
0!
0$
#2830000000
1!
b00000100 #
1$
b00000100 &
#2840000000
0!
0$
#2850000000
1!
b00000101 #
1$
b00000101 &
#2860000000
0!
0$
#2870000000
1!
b00000110 #
1$
b00000110 &
#2880000000
0!
0$
#2890000000
1!
b00000111 #
1$
b00000111 &
#2900000000
0!
0$
#2910000000
1!
b00001000 #
1$
b00001000 &
#2920000000
0!
0$
#2930000000
1!
b00001001 #
1$
b00001001 &
#2940000000
0!
0$
#2950000000
1!
b00001010 #
1$
b00001010 &
#2960000000
0!
0$
#2970000000
1!
b00001011 #
1$
b00001011 &
#2980000000
0!
0$
#2990000000
1!
b00001100 #
1$
b00001100 &
#3000000000
0!
0$
#3010000000
1!
b00001101 #
1$
b00001101 &
#3020000000
0!
0$
#3030000000
1!
b00001110 #
1$
b00001110 &
#3040000000
0!
0$
#3050000000
1!
b00001111 #
1$
b00001111 &
#3060000000
0!
0$
#3070000000
1!
b00010000 #
1$
b00010000 &
#3080000000
0!
0$
#3090000000
1!
b00010001 #
1$
b00010001 &
#3100000000
0!
0$
#3110000000
1!
b00010010 #
1$
b00010010 &
#3120000000
0!
0$
#3130000000
1!
b00010011 #
1$
b00010011 &
#3140000000
0!
0$
#3150000000
1!
b00010100 #
1$
b00010100 &
#3160000000
0!
0$
#3170000000
1!
b00010101 #
1$
b00010101 &
#3180000000
0!
0$
#3190000000
1!
b00010110 #
1$
b00010110 &
#3200000000
0!
0$
#3210000000
1!
b00010111 #
1$
b00010111 &
#3220000000
0!
0$
#3230000000
1!
b00011000 #
1$
b00011000 &
#3240000000
0!
0$
#3250000000
1!
b00011001 #
1$
b00011001 &
#3260000000
0!
0$
#3270000000
1!
b00011010 #
1$
b00011010 &
#3280000000
0!
0$
#3290000000
1!
b00011011 #
1$
b00011011 &
#3300000000
0!
0$
#3310000000
1!
b00011100 #
1$
b00011100 &
#3320000000
0!
0$
#3330000000
1!
b00011101 #
1$
b00011101 &
#3340000000
0!
0$
#3350000000
1!
b00011110 #
1$
b00011110 &
#3360000000
0!
0$
#3370000000
1!
b00011111 #
1$
b00011111 &
#3380000000
0!
0$
#3390000000
1!
b00100000 #
1$
b00100000 &
#3400000000
0!
0$
#3410000000
1!
b00100001 #
1$
b00100001 &
#3420000000
0!
0$
#3430000000
1!
b00100010 #
1$
b00100010 &
#3440000000
0!
0$
#3450000000
1!
b00100011 #
1$
b00100011 &
#3460000000
0!
0$
#3470000000
1!
b00100100 #
1$
b00100100 &
#3480000000
0!
0$
#3490000000
1!
b00100101 #
1$
b00100101 &
#3500000000
0!
0$
#3510000000
1!
b00100110 #
1$
b00100110 &
#3520000000
0!
0$
#3530000000
1!
b00100111 #
1$
b00100111 &
#3540000000
0!
0$
#3550000000
1!
b00101000 #
1$
b00101000 &
#3560000000
0!
0$
#3570000000
1!
b00101001 #
1$
b00101001 &
#3580000000
0!
0$
#3590000000
1!
b00101010 #
1$
b00101010 &
#3600000000
0!
0$
#3610000000
1!
b00101011 #
1$
b00101011 &
#3620000000
0!
0$
#3630000000
1!
b00101100 #
1$
b00101100 &
#3640000000
0!
0$
#3650000000
1!
b00101101 #
1$
b00101101 &
#3660000000
0!
0$
#3670000000
1!
b00101110 #
1$
b00101110 &
#3680000000
0!
0$
#3690000000
1!
b00101111 #
1$
b00101111 &
#3700000000
0!
0$
#3710000000
1!
b00110000 #
1$
b00110000 &
#3720000000
0!
0$
#3730000000
1!
b00110001 #
1$
b00110001 &
#3740000000
0!
0$
#3750000000
1!
b00110010 #
1$
b00110010 &
#3760000000
0!
0$
#3770000000
1!
b00110011 #
1$
b00110011 &
#3780000000
0!
0$
#3790000000
1!
b00110100 #
1$
b00110100 &
#3800000000
0!
0$
#3810000000
1!
b00110101 #
1$
b00110101 &
#3820000000
0!
0$
#3830000000
1!
b00110110 #
1$
b00110110 &
#3840000000
0!
0$
#3850000000
1!
b00110111 #
1$
b00110111 &
#3860000000
0!
0$
#3870000000
1!
b00111000 #
1$
b00111000 &
#3880000000
0!
0$
#3890000000
1!
b00111001 #
1$
b00111001 &
#3900000000
0!
0$
#3910000000
1!
b00111010 #
1$
b00111010 &
#3920000000
0!
0$
#3930000000
1!
b00111011 #
1$
b00111011 &
#3940000000
0!
0$
#3950000000
1!
b00111100 #
1$
b00111100 &
#3960000000
0!
0$
#3970000000
1!
b00111101 #
1$
b00111101 &
#3980000000
0!
0$
#3990000000
1!
b00111110 #
1$
b00111110 &
#4000000000
0!
0$
#4010000000
1!
b00111111 #
1$
b00111111 &
#4020000000
0!
0$
#4030000000
1!
b01000000 #
1$
b01000000 &
#4040000000
0!
0$
#4050000000
1!
b01000001 #
1$
b01000001 &
#4060000000
0!
0$
#4070000000
1!
b01000010 #
1$
b01000010 &
#4080000000
0!
0$
#4090000000
1!
b01000011 #
1$
b01000011 &
#4100000000
0!
0$
#4110000000
1!
b01000100 #
1$
b01000100 &
#4120000000
0!
0$
#4130000000
1!
b01000101 #
1$
b01000101 &
#4140000000
0!
0$
#4150000000
1!
b01000110 #
1$
b01000110 &
#4160000000
0!
0$
#4170000000
1!
b01000111 #
1$
b01000111 &
#4180000000
0!
0$
#4190000000
1!
b01001000 #
1$
b01001000 &
#4200000000
0!
0$
#4210000000
1!
b01001001 #
1$
b01001001 &
#4220000000
0!
0$
#4230000000
1!
b01001010 #
1$
b01001010 &
#4240000000
0!
0$
#4250000000
1!
b01001011 #
1$
b01001011 &
#4260000000
0!
0$
#4270000000
1!
b01001100 #
1$
b01001100 &
#4280000000
0!
0$
#4290000000
1!
b01001101 #
1$
b01001101 &
#4300000000
0!
0$
#4310000000
1!
b01001110 #
1$
b01001110 &
#4320000000
0!
0$
#4330000000
1!
b01001111 #
1$
b01001111 &
#4340000000
0!
0$
#4350000000
1!
b01010000 #
1$
b01010000 &
#4360000000
0!
0$
#4370000000
1!
b01010001 #
1$
b01010001 &
#4380000000
0!
0$
#4390000000
1!
b01010010 #
1$
b01010010 &
#4400000000
0!
0$
#4410000000
1!
b01010011 #
1$
b01010011 &
#4420000000
0!
0$
#4430000000
1!
b01010100 #
1$
b01010100 &
#4440000000
0!
0$
#4450000000
1!
b01010101 #
1$
b01010101 &
#4460000000
0!
0$
#4470000000
1!
b01010110 #
1$
b01010110 &
#4480000000
0!
0$
#4490000000
1!
b01010111 #
1$
b01010111 &
#4500000000
0!
0$
#4510000000
1!
b01011000 #
1$
b01011000 &
#4520000000
0!
0$
#4530000000
1!
b01011001 #
1$
b01011001 &
#4540000000
0!
0$
#4550000000
1!
b01011010 #
1$
b01011010 &
#4560000000
0!
0$
#4570000000
1!
b01011011 #
1$
b01011011 &
#4580000000
0!
0$
#4590000000
1!
b01011100 #
1$
b01011100 &
#4600000000
0!
0$
#4610000000
1!
b01011101 #
1$
b01011101 &
#4620000000
0!
0$
#4630000000
1!
b01011110 #
1$
b01011110 &
#4640000000
0!
0$
#4650000000
1!
b01011111 #
1$
b01011111 &
#4660000000
0!
0$
#4670000000
1!
b01100000 #
1$
b01100000 &
#4680000000
0!
0$
#4690000000
1!
b01100001 #
1$
b01100001 &
#4700000000
0!
0$
#4710000000
1!
b01100010 #
1$
b01100010 &
#4720000000
0!
0$
#4730000000
1!
b01100011 #
1$
b01100011 &
#4740000000
0!
0$
#4750000000
1!
b01100100 #
1$
b01100100 &
#4760000000
0!
0$
#4770000000
1!
b01100101 #
1$
b01100101 &
#4780000000
0!
0$
#4790000000
1!
b01100110 #
1$
b01100110 &
#4800000000
0!
0$
#4810000000
1!
b01100111 #
1$
b01100111 &
#4820000000
0!
0$
#4830000000
1!
b01101000 #
1$
b01101000 &
#4840000000
0!
0$
#4850000000
1!
b01101001 #
1$
b01101001 &
#4860000000
0!
0$
#4870000000
1!
b01101010 #
1$
b01101010 &
#4880000000
0!
0$
#4890000000
1!
b01101011 #
1$
b01101011 &
#4900000000
0!
0$
#4910000000
1!
b01101100 #
1$
b01101100 &
#4920000000
0!
0$
#4930000000
1!
b01101101 #
1$
b01101101 &
#4940000000
0!
0$
#4950000000
1!
b01101110 #
1$
b01101110 &
#4960000000
0!
0$
#4970000000
1!
b01101111 #
1$
b01101111 &
#4980000000
0!
0$
#4990000000
1!
b01110000 #
1$
b01110000 &
#5000000000
0!
0$
#5010000000
1!
b01110001 #
1$
b01110001 &
#5020000000
0!
0$
#5030000000
1!
b01110010 #
1$
b01110010 &
#5040000000
0!
0$
#5050000000
1!
b01110011 #
1$
b01110011 &
#5060000000
0!
0$
#5070000000
1!
b01110100 #
1$
b01110100 &
#5080000000
0!
0$
#5090000000
1!
b01110101 #
1$
b01110101 &
#5100000000
0!
0$
#5110000000
1!
b01110110 #
1$
b01110110 &
#5120000000
0!
0$
#5130000000
1!
b01110111 #
1$
b01110111 &
#5140000000
0!
0$
#5150000000
1!
b01111000 #
1$
b01111000 &
#5160000000
0!
0$
#5170000000
1!
b01111001 #
1$
b01111001 &
#5180000000
0!
0$
#5190000000
1!
b01111010 #
1$
b01111010 &
#5200000000
0!
0$
#5210000000
1!
b01111011 #
1$
b01111011 &
#5220000000
0!
0$
#5230000000
1!
b01111100 #
1$
b01111100 &
#5240000000
0!
0$
#5250000000
1!
b01111101 #
1$
b01111101 &
#5260000000
0!
0$
#5270000000
1!
b01111110 #
1$
b01111110 &
#5280000000
0!
0$
#5290000000
1!
b01111111 #
1$
b01111111 &
#5300000000
0!
0$
#5310000000
1!
b10000000 #
1$
b10000000 &
#5320000000
0!
0$
#5330000000
1!
b10000001 #
1$
b10000001 &
#5340000000
0!
0$
#5350000000
1!
b10000010 #
1$
b10000010 &
#5360000000
0!
0$
#5370000000
1!
b10000011 #
1$
b10000011 &
#5380000000
0!
0$
#5390000000
1!
b10000100 #
1$
b10000100 &
#5400000000
0!
0$
#5410000000
1!
b10000101 #
1$
b10000101 &
#5420000000
0!
0$
#5430000000
1!
b10000110 #
1$
b10000110 &
#5440000000
0!
0$
#5450000000
1!
b10000111 #
1$
b10000111 &
#5460000000
0!
0$
#5470000000
1!
b10001000 #
1$
b10001000 &
#5480000000
0!
0$
#5490000000
1!
b10001001 #
1$
b10001001 &
#5500000000
0!
0$
#5510000000
1!
b10001010 #
1$
b10001010 &
#5520000000
0!
0$
#5530000000
1!
b10001011 #
1$
b10001011 &
#5540000000
0!
0$
#5550000000
1!
b10001100 #
1$
b10001100 &
#5560000000
0!
0$
#5570000000
1!
b10001101 #
1$
b10001101 &
#5580000000
0!
0$
#5590000000
1!
b10001110 #
1$
b10001110 &
#5600000000
0!
0$
#5610000000
1!
b10001111 #
1$
b10001111 &
#5620000000
0!
0$
#5630000000
1!
b10010000 #
1$
b10010000 &
#5640000000
0!
0$
#5650000000
1!
b10010001 #
1$
b10010001 &
#5660000000
0!
0$
#5670000000
1!
b10010010 #
1$
b10010010 &
#5680000000
0!
0$
#5690000000
1!
b10010011 #
1$
b10010011 &
#5700000000
0!
0$
#5710000000
1!
b10010100 #
1$
b10010100 &
#5720000000
0!
0$
#5730000000
1!
b10010101 #
1$
b10010101 &
#5740000000
0!
0$
#5750000000
1!
b10010110 #
1$
b10010110 &
#5760000000
0!
0$
#5770000000
1!
b10010111 #
1$
b10010111 &
#5780000000
0!
0$
#5790000000
1!
b10011000 #
1$
b10011000 &
#5800000000
0!
0$
#5810000000
1!
b10011001 #
1$
b10011001 &
#5820000000
0!
0$
#5830000000
1!
b10011010 #
1$
b10011010 &
#5840000000
0!
0$
#5850000000
1!
b10011011 #
1$
b10011011 &
#5860000000
0!
0$
#5870000000
1!
b10011100 #
1$
b10011100 &
#5880000000
0!
0$
#5890000000
1!
b10011101 #
1$
b10011101 &
#5900000000
0!
0$
#5910000000
1!
b10011110 #
1$
b10011110 &
#5920000000
0!
0$
#5930000000
1!
b10011111 #
1$
b10011111 &
#5940000000
0!
0$
#5950000000
1!
b10100000 #
1$
b10100000 &
#5960000000
0!
0$
#5970000000
1!
b10100001 #
1$
b10100001 &
#5980000000
0!
0$
#5990000000
1!
b10100010 #
1$
b10100010 &
#6000000000
0!
0$
#6010000000
1!
b10100011 #
1$
b10100011 &
#6020000000
0!
0$
#6030000000
1!
b10100100 #
1$
b10100100 &
#6040000000
0!
0$
#6050000000
1!
b10100101 #
1$
b10100101 &
#6060000000
0!
0$
#6070000000
1!
b10100110 #
1$
b10100110 &
#6080000000
0!
0$
#6090000000
1!
b10100111 #
1$
b10100111 &
#6100000000
0!
0$
#6110000000
1!
b10101000 #
1$
b10101000 &
#6120000000
0!
0$
#6130000000
1!
b10101001 #
1$
b10101001 &
#6140000000
0!
0$
#6150000000
1!
b10101010 #
1$
b10101010 &
#6160000000
0!
0$
#6170000000
1!
b10101011 #
1$
b10101011 &
#6180000000
0!
0$
#6190000000
1!
b10101100 #
1$
b10101100 &
#6200000000
0!
0$
#6210000000
1!
b10101101 #
1$
b10101101 &
#6220000000
0!
0$
#6230000000
1!
b10101110 #
1$
b10101110 &
#6240000000
0!
0$
#6250000000
1!
b10101111 #
1$
b10101111 &
#6260000000
0!
0$
#6270000000
1!
b10110000 #
1$
b10110000 &
#6280000000
0!
0$
#6290000000
1!
b10110001 #
1$
b10110001 &
#6300000000
0!
0$
#6310000000
1!
b10110010 #
1$
b10110010 &
#6320000000
0!
0$
#6330000000
1!
b10110011 #
1$
b10110011 &
#6340000000
0!
0$
#6350000000
1!
b10110100 #
1$
b10110100 &
#6360000000
0!
0$
#6370000000
1!
b10110101 #
1$
b10110101 &
#6380000000
0!
0$
#6390000000
1!
b10110110 #
1$
b10110110 &
#6400000000
0!
0$
#6410000000
1!
b10110111 #
1$
b10110111 &
#6420000000
0!
0$
#6430000000
1!
b10111000 #
1$
b10111000 &
#6440000000
0!
0$
#6450000000
1!
b10111001 #
1$
b10111001 &
#6460000000
0!
0$
#6470000000
1!
b10111010 #
1$
b10111010 &
#6480000000
0!
0$
#6490000000
1!
b10111011 #
1$
b10111011 &
#6500000000
0!
0$
#6510000000
1!
b10111100 #
1$
b10111100 &
#6520000000
0!
0$
#6530000000
1!
b10111101 #
1$
b10111101 &
#6540000000
0!
0$
#6550000000
1!
b10111110 #
1$
b10111110 &
#6560000000
0!
0$
#6570000000
1!
b10111111 #
1$
b10111111 &
#6580000000
0!
0$
#6590000000
1!
b11000000 #
1$
b11000000 &
#6600000000
0!
0$
#6610000000
1!
b11000001 #
1$
b11000001 &
#6620000000
0!
0$
#6630000000
1!
b11000010 #
1$
b11000010 &
#6640000000
0!
0$
#6650000000
1!
b11000011 #
1$
b11000011 &
#6660000000
0!
0$
#6670000000
1!
b11000100 #
1$
b11000100 &
#6680000000
0!
0$
#6690000000
1!
b11000101 #
1$
b11000101 &
#6700000000
0!
0$
#6710000000
1!
b11000110 #
1$
b11000110 &
#6720000000
0!
0$
#6730000000
1!
b11000111 #
1$
b11000111 &
#6740000000
0!
0$
#6750000000
1!
b11001000 #
1$
b11001000 &
#6760000000
0!
0$
#6770000000
1!
b11001001 #
1$
b11001001 &
#6780000000
0!
0$
#6790000000
1!
b11001010 #
1$
b11001010 &
#6800000000
0!
0$
#6810000000
1!
b11001011 #
1$
b11001011 &
#6820000000
0!
0$
#6830000000
1!
b11001100 #
1$
b11001100 &
#6840000000
0!
0$
#6850000000
1!
b11001101 #
1$
b11001101 &
#6860000000
0!
0$
#6870000000
1!
b11001110 #
1$
b11001110 &
#6880000000
0!
0$
#6890000000
1!
b11001111 #
1$
b11001111 &
#6900000000
0!
0$
#6910000000
1!
b11010000 #
1$
b11010000 &
#6920000000
0!
0$
#6930000000
1!
b11010001 #
1$
b11010001 &
#6940000000
0!
0$
#6950000000
1!
b11010010 #
1$
b11010010 &
#6960000000
0!
0$
#6970000000
1!
b11010011 #
1$
b11010011 &
#6980000000
0!
0$
#6990000000
1!
b11010100 #
1$
b11010100 &
#7000000000
0!
0$
#7010000000
1!
b11010101 #
1$
b11010101 &
#7020000000
0!
0$
#7030000000
1!
b11010110 #
1$
b11010110 &
#7040000000
0!
0$
#7050000000
1!
b11010111 #
1$
b11010111 &
#7060000000
0!
0$
#7070000000
1!
b11011000 #
1$
b11011000 &
#7080000000
0!
0$
#7090000000
1!
b11011001 #
1$
b11011001 &
